vox_cards/__init__.py
vox_cards/card.py
vox_cards/deck.py
vox_cards/hand.py
vox_cards-0.1.8.dist-info/LICENSE
vox_cards-0.1.8.dist-info/METADATA
vox_cards-0.1.8.dist-info/WHEEL
vox_cards-0.1.8.dist-info/top_level.txt
vox_cards-0.1.8.dist-info/RECORD
