Metadata-Version: 2.1
Name: vox-cards
Version: 0.1.8
Summary: A dependancy free deck, card, and hand manager.
Home-page: https://github.com/voxlight/vox_cards
Author: VoxLight
Author-email: tkkt392@gmail.com
License: UNKNOWN
Platform: UNKNOWN
Classifier: Programming Language :: Python :: 3
Classifier: License :: OSI Approved :: MIT License
Classifier: Operating System :: OS Independent
Requires-Python: >=3.6
